{
  "best_metric": null,
  "best_model_checkpoint": null,
  "epoch": 1.0,
  "eval_steps": 100,
  "global_step": 625,
  "is_hyper_param_search": false,
  "is_local_process_zero": true,
  "is_world_process_zero": true,
  "log_history": [
    {
      "epoch": 0.016,
      "grad_norm": 601.0301354885145,
      "learning_rate": 1.597444089456869e-07,
      "loss": 4.0921,
      "step": 10
    },
    {
      "epoch": 0.032,
      "grad_norm": 356.3570736726269,
      "learning_rate": 3.194888178913738e-07,
      "loss": 2.953,
      "step": 20
    },
    {
      "epoch": 0.048,
      "grad_norm": 56.175845198767284,
      "learning_rate": 4.792332268370608e-07,
      "loss": 0.702,
      "step": 30
    },
    {
      "epoch": 0.064,
      "grad_norm": 48.020652223797825,
      "learning_rate": 6.389776357827476e-07,
      "loss": 0.3279,
      "step": 40
    },
    {
      "epoch": 0.08,
      "grad_norm": 33.450303374662994,
      "learning_rate": 7.987220447284346e-07,
      "loss": 0.3465,
      "step": 50
    },
    {
      "epoch": 0.096,
      "grad_norm": 32.158866545845534,
      "learning_rate": 9.584664536741215e-07,
      "loss": 0.2646,
      "step": 60
    },
    {
      "epoch": 0.112,
      "grad_norm": 18.97918403225882,
      "learning_rate": 1.1182108626198083e-06,
      "loss": 0.2694,
      "step": 70
    },
    {
      "epoch": 0.128,
      "grad_norm": 20.126611364284603,
      "learning_rate": 1.2779552715654952e-06,
      "loss": 0.2425,
      "step": 80
    },
    {
      "epoch": 0.144,
      "grad_norm": 24.033084478087794,
      "learning_rate": 1.4376996805111824e-06,
      "loss": 0.2084,
      "step": 90
    },
    {
      "epoch": 0.16,
      "grad_norm": 30.641268312090553,
      "learning_rate": 1.5974440894568691e-06,
      "loss": 0.1875,
      "step": 100
    },
    {
      "epoch": 0.16,
      "eval_FoVer_PRM_FormalLogic_10k_Llama-3.1-8B-Instruct_validation_loss": 0.32603776454925537,
      "eval_FoVer_PRM_FormalLogic_10k_Llama-3.1-8B-Instruct_validation_runtime": 18.1121,
      "eval_FoVer_PRM_FormalLogic_10k_Llama-3.1-8B-Instruct_validation_samples_per_second": 49.691,
      "eval_FoVer_PRM_FormalLogic_10k_Llama-3.1-8B-Instruct_validation_steps_per_second": 3.147,
      "step": 100
    },
    {
      "epoch": 0.176,
      "grad_norm": 32.579609015780896,
      "learning_rate": 1.757188498402556e-06,
      "loss": 0.2098,
      "step": 110
    },
    {
      "epoch": 0.192,
      "grad_norm": 19.733711918957304,
      "learning_rate": 1.916932907348243e-06,
      "loss": 0.1727,
      "step": 120
    },
    {
      "epoch": 0.208,
      "grad_norm": 35.64853415415562,
      "learning_rate": 2.07667731629393e-06,
      "loss": 0.1626,
      "step": 130
    },
    {
      "epoch": 0.224,
      "grad_norm": 12.610814949869416,
      "learning_rate": 2.2364217252396165e-06,
      "loss": 0.2073,
      "step": 140
    },
    {
      "epoch": 0.24,
      "grad_norm": 23.93635797911378,
      "learning_rate": 2.396166134185304e-06,
      "loss": 0.1684,
      "step": 150
    },
    {
      "epoch": 0.256,
      "grad_norm": 10.676507510156133,
      "learning_rate": 2.5559105431309904e-06,
      "loss": 0.2091,
      "step": 160
    },
    {
      "epoch": 0.272,
      "grad_norm": 23.715376248976945,
      "learning_rate": 2.7156549520766774e-06,
      "loss": 0.1676,
      "step": 170
    },
    {
      "epoch": 0.288,
      "grad_norm": 18.622421879095644,
      "learning_rate": 2.8753993610223648e-06,
      "loss": 0.1628,
      "step": 180
    },
    {
      "epoch": 0.304,
      "grad_norm": 39.949449585872074,
      "learning_rate": 3.0351437699680513e-06,
      "loss": 0.1859,
      "step": 190
    },
    {
      "epoch": 0.32,
      "grad_norm": 18.682139213068957,
      "learning_rate": 3.1948881789137383e-06,
      "loss": 0.176,
      "step": 200
    },
    {
      "epoch": 0.32,
      "eval_FoVer_PRM_FormalLogic_10k_Llama-3.1-8B-Instruct_validation_loss": 0.2891504168510437,
      "eval_FoVer_PRM_FormalLogic_10k_Llama-3.1-8B-Instruct_validation_runtime": 18.3315,
      "eval_FoVer_PRM_FormalLogic_10k_Llama-3.1-8B-Instruct_validation_samples_per_second": 49.096,
      "eval_FoVer_PRM_FormalLogic_10k_Llama-3.1-8B-Instruct_validation_steps_per_second": 3.109,
      "step": 200
    },
    {
      "epoch": 0.336,
      "grad_norm": 18.069273327787613,
      "learning_rate": 3.3546325878594257e-06,
      "loss": 0.1493,
      "step": 210
    },
    {
      "epoch": 0.352,
      "grad_norm": 3.7214317830606567,
      "learning_rate": 3.514376996805112e-06,
      "loss": 0.123,
      "step": 220
    },
    {
      "epoch": 0.368,
      "grad_norm": 28.34675973758075,
      "learning_rate": 3.674121405750799e-06,
      "loss": 0.1726,
      "step": 230
    },
    {
      "epoch": 0.384,
      "grad_norm": 30.645620349896358,
      "learning_rate": 3.833865814696486e-06,
      "loss": 0.2495,
      "step": 240
    },
    {
      "epoch": 0.4,
      "grad_norm": 11.773154210093049,
      "learning_rate": 3.9936102236421735e-06,
      "loss": 0.2136,
      "step": 250
    },
    {
      "epoch": 0.416,
      "grad_norm": 32.20661617986974,
      "learning_rate": 4.15335463258786e-06,
      "loss": 0.2027,
      "step": 260
    },
    {
      "epoch": 0.432,
      "grad_norm": 23.218843469167975,
      "learning_rate": 4.3130990415335465e-06,
      "loss": 0.1726,
      "step": 270
    },
    {
      "epoch": 0.448,
      "grad_norm": 11.303155599932328,
      "learning_rate": 4.472843450479233e-06,
      "loss": 0.1766,
      "step": 280
    },
    {
      "epoch": 0.464,
      "grad_norm": 4.393140474572815,
      "learning_rate": 4.6325878594249205e-06,
      "loss": 0.1558,
      "step": 290
    },
    {
      "epoch": 0.48,
      "grad_norm": 18.836855918935754,
      "learning_rate": 4.792332268370608e-06,
      "loss": 0.1469,
      "step": 300
    },
    {
      "epoch": 0.48,
      "eval_FoVer_PRM_FormalLogic_10k_Llama-3.1-8B-Instruct_validation_loss": 0.3724803626537323,
      "eval_FoVer_PRM_FormalLogic_10k_Llama-3.1-8B-Instruct_validation_runtime": 18.0821,
      "eval_FoVer_PRM_FormalLogic_10k_Llama-3.1-8B-Instruct_validation_samples_per_second": 49.773,
      "eval_FoVer_PRM_FormalLogic_10k_Llama-3.1-8B-Instruct_validation_steps_per_second": 3.152,
      "step": 300
    },
    {
      "epoch": 0.496,
      "grad_norm": 9.43254954838442,
      "learning_rate": 4.952076677316294e-06,
      "loss": 0.1964,
      "step": 310
    },
    {
      "epoch": 0.512,
      "grad_norm": 17.08910086162519,
      "learning_rate": 4.887820512820513e-06,
      "loss": 0.1599,
      "step": 320
    },
    {
      "epoch": 0.528,
      "grad_norm": 21.795017197323247,
      "learning_rate": 4.727564102564103e-06,
      "loss": 0.2009,
      "step": 330
    },
    {
      "epoch": 0.544,
      "grad_norm": 11.586075257468492,
      "learning_rate": 4.567307692307692e-06,
      "loss": 0.1639,
      "step": 340
    },
    {
      "epoch": 0.56,
      "grad_norm": 16.843137764781083,
      "learning_rate": 4.4070512820512826e-06,
      "loss": 0.1818,
      "step": 350
    },
    {
      "epoch": 0.576,
      "grad_norm": 18.639077859968534,
      "learning_rate": 4.246794871794872e-06,
      "loss": 0.1813,
      "step": 360
    },
    {
      "epoch": 0.592,
      "grad_norm": 17.567579161818664,
      "learning_rate": 4.086538461538462e-06,
      "loss": 0.1476,
      "step": 370
    },
    {
      "epoch": 0.608,
      "grad_norm": 7.954850443074088,
      "learning_rate": 3.926282051282051e-06,
      "loss": 0.1097,
      "step": 380
    },
    {
      "epoch": 0.624,
      "grad_norm": 7.567906229319271,
      "learning_rate": 3.766025641025641e-06,
      "loss": 0.1074,
      "step": 390
    },
    {
      "epoch": 0.64,
      "grad_norm": 11.42601728140461,
      "learning_rate": 3.605769230769231e-06,
      "loss": 0.0992,
      "step": 400
    },
    {
      "epoch": 0.64,
      "eval_FoVer_PRM_FormalLogic_10k_Llama-3.1-8B-Instruct_validation_loss": 0.36374905705451965,
      "eval_FoVer_PRM_FormalLogic_10k_Llama-3.1-8B-Instruct_validation_runtime": 18.1222,
      "eval_FoVer_PRM_FormalLogic_10k_Llama-3.1-8B-Instruct_validation_samples_per_second": 49.663,
      "eval_FoVer_PRM_FormalLogic_10k_Llama-3.1-8B-Instruct_validation_steps_per_second": 3.145,
      "step": 400
    },
    {
      "epoch": 0.656,
      "grad_norm": 16.287114278981864,
      "learning_rate": 3.4455128205128206e-06,
      "loss": 0.121,
      "step": 410
    },
    {
      "epoch": 0.672,
      "grad_norm": 13.944131155801056,
      "learning_rate": 3.2852564102564106e-06,
      "loss": 0.1568,
      "step": 420
    },
    {
      "epoch": 0.688,
      "grad_norm": 6.063272339416683,
      "learning_rate": 3.125e-06,
      "loss": 0.118,
      "step": 430
    },
    {
      "epoch": 0.704,
      "grad_norm": 8.189662248692626,
      "learning_rate": 2.96474358974359e-06,
      "loss": 0.1208,
      "step": 440
    },
    {
      "epoch": 0.72,
      "grad_norm": 12.647752745226244,
      "learning_rate": 2.8044871794871797e-06,
      "loss": 0.1033,
      "step": 450
    },
    {
      "epoch": 0.736,
      "grad_norm": 2.536254670379757,
      "learning_rate": 2.6442307692307696e-06,
      "loss": 0.1181,
      "step": 460
    },
    {
      "epoch": 0.752,
      "grad_norm": 15.740462862584836,
      "learning_rate": 2.483974358974359e-06,
      "loss": 0.0985,
      "step": 470
    },
    {
      "epoch": 0.768,
      "grad_norm": 24.349992147695318,
      "learning_rate": 2.323717948717949e-06,
      "loss": 0.1244,
      "step": 480
    },
    {
      "epoch": 0.784,
      "grad_norm": 24.1124331204137,
      "learning_rate": 2.1634615384615387e-06,
      "loss": 0.1019,
      "step": 490
    },
    {
      "epoch": 0.8,
      "grad_norm": 7.229299658868204,
      "learning_rate": 2.0032051282051286e-06,
      "loss": 0.0906,
      "step": 500
    },
    {
      "epoch": 0.8,
      "eval_FoVer_PRM_FormalLogic_10k_Llama-3.1-8B-Instruct_validation_loss": 0.337257981300354,
      "eval_FoVer_PRM_FormalLogic_10k_Llama-3.1-8B-Instruct_validation_runtime": 18.8618,
      "eval_FoVer_PRM_FormalLogic_10k_Llama-3.1-8B-Instruct_validation_samples_per_second": 47.715,
      "eval_FoVer_PRM_FormalLogic_10k_Llama-3.1-8B-Instruct_validation_steps_per_second": 3.022,
      "step": 500
    },
    {
      "epoch": 0.816,
      "grad_norm": 5.182174686062401,
      "learning_rate": 1.8429487179487182e-06,
      "loss": 0.1208,
      "step": 510
    },
    {
      "epoch": 0.832,
      "grad_norm": 21.097339317455265,
      "learning_rate": 1.682692307692308e-06,
      "loss": 0.1333,
      "step": 520
    },
    {
      "epoch": 0.848,
      "grad_norm": 10.688139908364706,
      "learning_rate": 1.5224358974358975e-06,
      "loss": 0.0861,
      "step": 530
    },
    {
      "epoch": 0.864,
      "grad_norm": 8.295035054255722,
      "learning_rate": 1.3621794871794872e-06,
      "loss": 0.0889,
      "step": 540
    },
    {
      "epoch": 0.88,
      "grad_norm": 15.04701203196719,
      "learning_rate": 1.201923076923077e-06,
      "loss": 0.0833,
      "step": 550
    },
    {
      "epoch": 0.896,
      "grad_norm": 13.527321298425239,
      "learning_rate": 1.0416666666666667e-06,
      "loss": 0.0614,
      "step": 560
    },
    {
      "epoch": 0.912,
      "grad_norm": 12.941155467039758,
      "learning_rate": 8.814102564102566e-07,
      "loss": 0.0621,
      "step": 570
    },
    {
      "epoch": 0.928,
      "grad_norm": 13.952249489431852,
      "learning_rate": 7.211538461538461e-07,
      "loss": 0.0991,
      "step": 580
    },
    {
      "epoch": 0.944,
      "grad_norm": 62.09908887402571,
      "learning_rate": 5.60897435897436e-07,
      "loss": 0.0676,
      "step": 590
    },
    {
      "epoch": 0.96,
      "grad_norm": 10.39386269422057,
      "learning_rate": 4.006410256410257e-07,
      "loss": 0.0738,
      "step": 600
    },
    {
      "epoch": 0.96,
      "eval_FoVer_PRM_FormalLogic_10k_Llama-3.1-8B-Instruct_validation_loss": 0.18030543625354767,
      "eval_FoVer_PRM_FormalLogic_10k_Llama-3.1-8B-Instruct_validation_runtime": 18.0166,
      "eval_FoVer_PRM_FormalLogic_10k_Llama-3.1-8B-Instruct_validation_samples_per_second": 49.954,
      "eval_FoVer_PRM_FormalLogic_10k_Llama-3.1-8B-Instruct_validation_steps_per_second": 3.164,
      "step": 600
    },
    {
      "epoch": 0.976,
      "grad_norm": 26.063366473418316,
      "learning_rate": 2.403846153846154e-07,
      "loss": 0.048,
      "step": 610
    },
    {
      "epoch": 0.992,
      "grad_norm": 8.013973759411437,
      "learning_rate": 8.012820512820512e-08,
      "loss": 0.0526,
      "step": 620
    },
    {
      "epoch": 1.0,
      "step": 625,
      "total_flos": 20535155097600.0,
      "train_loss": 0.2704116596698761,
      "train_runtime": 1842.9214,
      "train_samples_per_second": 10.852,
      "train_steps_per_second": 0.339
    }
  ],
  "logging_steps": 10,
  "max_steps": 625,
  "num_input_tokens_seen": 0,
  "num_train_epochs": 1,
  "save_steps": 1000000000,
  "stateful_callbacks": {
    "TrainerControl": {
      "args": {
        "should_epoch_stop": false,
        "should_evaluate": false,
        "should_log": false,
        "should_save": true,
        "should_training_stop": true
      },
      "attributes": {}
    }
  },
  "total_flos": 20535155097600.0,
  "train_batch_size": 4,
  "trial_name": null,
  "trial_params": null
}
